YangzhongyiYixingHuandouShizhan/README.md
YangzhongyiYixingHuandouShizhan/__init__.py
YangzhongyiYixingHuandouShizhan/__main__.py
YangzhongyiYixingHuandouShizhan/file.pdf
YangzhongyiYixingHuandouShizhan/index.html
yangzhongyi_yixing_huandou_shizhan-2022.10.22.0.dist-info/METADATA
yangzhongyi_yixing_huandou_shizhan-2022.10.22.0.dist-info/WHEEL
yangzhongyi_yixing_huandou_shizhan-2022.10.22.0.dist-info/entry_points.txt
yangzhongyi_yixing_huandou_shizhan-2022.10.22.0.dist-info/top_level.txt
yangzhongyi_yixing_huandou_shizhan-2022.10.22.0.dist-info/RECORD
